{
  "name" : "jest-watcher",
  "description" : "Delightful JavaScript Testing.",
  "version" : "24.9.0",
  "homepage" : "https://jestjs.io/",
  "repository" : {
    "type" : "git",
    "url" : "https://github.com/facebook/jest",
    "directory" : "packages/jest-watcher"
  },
  "bugs" : {
    "url" : "https://github.com/facebook/jest/issues"
  },
  "engines" : {
    "node" : ">= 6"
  },
  "main" : "build/index.js",
  "dist" : {
    "tarball" : "https://artifacts.developer.gov.bc.ca/artifactory/api/npm//npm-remote-cache/jest-watcher/-/jest-watcher-24.9.0.tgz",
    "shasum" : "4b56e5d1ceff005f5b88e528dc9afc8dd4ed2b3b"
  },
  "dependencies" : {
    "@jest/test-result" : "^24.9.0",
    "@jest/types" : "^24.9.0",
    "@types/yargs" : "^13.0.0",
    "ansi-escapes" : "^3.0.0",
    "chalk" : "^2.0.1",
    "jest-util" : "^24.9.0",
    "string-length" : "^2.0.0"
  },
  "devDependencies" : {
    "@types/ansi-escapes" : "^3.0.0",
    "@types/string-length" : "^2.0.0"
  },
  "license" : "MIT",
  "scripts" : {
  },
  "publishConfig" : {
    "access" : "public"
  },
  "gitHead" : "9ad0f4bc6b8bdd94989804226c28c9960d9da7d1"
}