<?xml version='1.0' encoding='UTF-8'?>
<artifactory-file>
  <repoPath>
    <repoKey>npm-remote-cache</repoKey>
    <path>regex-not/-/regex-not-1.0.2.tgz</path>
    <folder>false</folder>
  </repoPath>
  <name>regex-not-1.0.2.tgz</name>
  <created>1576003476729</created>
  <lastModified>1527435823000</lastModified>
  <size>3357</size>
  <additionalInfo>
    <createdBy>dgqzdw</createdBy>
    <modifiedBy>dgqzdw</modifiedBy>
    <lastUpdated>1576003476729</lastUpdated>
    <checksumsInfo>
      <checksums>
        <checksum>
          <type>sha1</type>
          <actual>1f4ece27e00b0b65e0247a6810e6a85d83a5752c</actual>
        </checksum>
        <checksum>
          <type>md5</type>
          <actual>e54f51e5d23c17edae9f9d199b337531</actual>
        </checksum>
        <checksum>
          <type>sha256</type>
          <original>NO_ORIG</original>
          <actual>fa4448bb964e8f97905f8e557d529884f08dea1a5e61e88d7589819967bef276</actual>
        </checksum>
      </checksums>
    </checksumsInfo>
  </additionalInfo>
</artifactory-file>