<?xml version='1.0' encoding='UTF-8'?>
<artifactory-file>
  <repoPath>
    <repoKey>npm-remote-cache</repoKey>
    <path>.npm/function-bind/function-bind-1.1.1.json</path>
    <folder>false</folder>
  </repoPath>
  <name>function-bind-1.1.1.json</name>
  <created>1576003452860</created>
  <lastModified>1576003452836</lastModified>
  <size>1638</size>
  <additionalInfo>
    <createdBy>_system_</createdBy>
    <modifiedBy>_system_</modifiedBy>
    <lastUpdated>1576003452860</lastUpdated>
    <checksumsInfo>
      <checksums>
        <checksum>
          <type>sha1</type>
          <original>NO_ORIG</original>
          <actual>6dba014674b419daffcb4704f087f7b61d9ad1f5</actual>
        </checksum>
        <checksum>
          <type>md5</type>
          <original>NO_ORIG</original>
          <actual>66a7f751cd7dd1ea99a923c04ee8b53f</actual>
        </checksum>
        <checksum>
          <type>sha256</type>
          <original>NO_ORIG</original>
          <actual>ac6ccff7a7ea8236ede2ccc3b8ed27cf524027e63f3c725b9f31884dbc155bf8</actual>
        </checksum>
      </checksums>
    </checksumsInfo>
  </additionalInfo>
</artifactory-file>