<?xml version='1.0' encoding='UTF-8'?>
<artifactory-file>
  <repoPath>
    <repoKey>npm-remote-cache</repoKey>
    <path>.npm/is-data-descriptor/is-data-descriptor-0.1.4.json</path>
    <folder>false</folder>
  </repoPath>
  <name>is-data-descriptor-0.1.4.json</name>
  <created>1576003664800</created>
  <lastModified>1576003664779</lastModified>
  <size>1291</size>
  <additionalInfo>
    <createdBy>_system_</createdBy>
    <modifiedBy>_system_</modifiedBy>
    <lastUpdated>1576003664801</lastUpdated>
    <checksumsInfo>
      <checksums>
        <checksum>
          <type>sha1</type>
          <original>NO_ORIG</original>
          <actual>3909c7869831669e79758c0d59ba5d5ff0422653</actual>
        </checksum>
        <checksum>
          <type>md5</type>
          <original>NO_ORIG</original>
          <actual>9a0cf144e3ebd492db80efe18d4320be</actual>
        </checksum>
        <checksum>
          <type>sha256</type>
          <original>NO_ORIG</original>
          <actual>afecf34530f6b185510c25492974282d41fb53a07735bdf75f6862828aa39f76</actual>
        </checksum>
      </checksums>
    </checksumsInfo>
  </additionalInfo>
</artifactory-file>