<?xml version='1.0' encoding='UTF-8'?>
<artifactory-folder>
  <repoPath>
    <repoKey>pypi-remote-cache</repoKey>
    <path>7d/4b/cdf1113a0e88b641893b814e9c36f69a6fda28cd88b62c7f0d858cde3166</path>
    <folder>true</folder>
  </repoPath>
  <name>cdf1113a0e88b641893b814e9c36f69a6fda28cd88b62c7f0d858cde3166</name>
  <created>1574023491049</created>
  <lastModified>1574023491049</lastModified>
  <additionalInfo>
    <createdBy>uhdbvk</createdBy>
    <modifiedBy>uhdbvk</modifiedBy>
    <lastUpdated>1574023491049</lastUpdated>
  </additionalInfo>
</artifactory-folder>