<?xml version='1.0' encoding='UTF-8'?>
<artifactory-file>
  <repoPath>
    <repoKey>pypi-remote-cache</repoKey>
    <path>.pypi/pyflakes.html</path>
    <folder>false</folder>
  </repoPath>
  <name>pyflakes.html</name>
  <created>1574023488298</created>
  <lastModified>1582154364315</lastModified>
  <size>11590</size>
  <additionalInfo>
    <createdBy>uhdbvk</createdBy>
    <modifiedBy>uhdbvk</modifiedBy>
    <lastUpdated>1582154364363</lastUpdated>
    <checksumsInfo>
      <checksums>
        <checksum>
          <type>sha1</type>
          <actual>292c8e7830eaeac493c94705dc226e5ae28e1c9d</actual>
        </checksum>
        <checksum>
          <type>md5</type>
          <actual>e590d55f6a6484b931ba711d0d35cb14</actual>
        </checksum>
        <checksum>
          <type>sha256</type>
          <original>NO_ORIG</original>
          <actual>3c586e2d4e8c94019b125bc87a202641f2486454ed31d52b1e54704723e49681</actual>
        </checksum>
      </checksums>
    </checksumsInfo>
  </additionalInfo>
</artifactory-file>