<?xml version='1.0' encoding='UTF-8'?>
<artifactory-file>
  <repoPath>
    <repoKey>npm-remote-cache</repoKey>
    <path>.npm/@cnakazawa/watch/@cnakazawa/watch-1.0.3.json</path>
    <folder>false</folder>
  </repoPath>
  <name>watch-1.0.3.json</name>
  <created>1576008551073</created>
  <lastModified>1576008550377</lastModified>
  <size>1082</size>
  <additionalInfo>
    <createdBy>_system_</createdBy>
    <modifiedBy>_system_</modifiedBy>
    <lastUpdated>1576008551075</lastUpdated>
    <checksumsInfo>
      <checksums>
        <checksum>
          <type>sha1</type>
          <original>NO_ORIG</original>
          <actual>c188949d1ffc56a364ffb3f89eb0e0450ac402c8</actual>
        </checksum>
        <checksum>
          <type>md5</type>
          <original>NO_ORIG</original>
          <actual>4bad005d4918158f6d3ad47308e579c1</actual>
        </checksum>
        <checksum>
          <type>sha256</type>
          <original>NO_ORIG</original>
          <actual>397fe76f9e63b61e9ee90a9590689f6826cd694a9a5ff3024e31057ce5b0247d</actual>
        </checksum>
      </checksums>
    </checksumsInfo>
  </additionalInfo>
</artifactory-file>