<?xml version='1.0' encoding='UTF-8'?>
<artifactory-file>
  <repoPath>
    <repoKey>nuget-remote-cache</repoKey>
    <path>Microsoft.NETCore.Platforms.1.1.0.nupkg</path>
    <folder>false</folder>
  </repoPath>
  <name>Microsoft.NETCore.Platforms.1.1.0.nupkg</name>
  <created>1578432197598</created>
  <lastModified>1545092015000</lastModified>
  <size>17960</size>
  <additionalInfo>
    <createdBy>uaxfwa</createdBy>
    <modifiedBy>uaxfwa</modifiedBy>
    <lastUpdated>1578432197599</lastUpdated>
    <checksumsInfo>
      <checksums>
        <checksum>
          <type>sha1</type>
          <actual>75d5b7cb644c86346e6e5eb251b64f96723a25a3</actual>
        </checksum>
        <checksum>
          <type>md5</type>
          <actual>cca9ed659ebfaac51ebd470acff84e2d</actual>
        </checksum>
        <checksum>
          <type>sha256</type>
          <original>NO_ORIG</original>
          <actual>15e338d24b5c39b4099389cc612841eb51ff13c07bb4829f97d39b27420e7023</actual>
        </checksum>
      </checksums>
    </checksumsInfo>
  </additionalInfo>
</artifactory-file>