<?xml version='1.0' encoding='UTF-8'?>
<artifactory-file>
  <repoPath>
    <repoKey>npm-remote-cache</repoKey>
    <path>.npm/glogg/package.json</path>
    <folder>false</folder>
  </repoPath>
  <name>package.json</name>
  <created>1576003437692</created>
  <lastModified>1546560834000</lastModified>
  <size>10788</size>
  <additionalInfo>
    <createdBy>dgqzdw</createdBy>
    <modifiedBy>dgqzdw</modifiedBy>
    <lastUpdated>1586464325030</lastUpdated>
    <checksumsInfo>
      <checksums>
        <checksum>
          <type>sha1</type>
          <actual>4f0b648104d2a748650a1c0667a763539dfbcbff</actual>
        </checksum>
        <checksum>
          <type>md5</type>
          <actual>298e00f565f7c3b0c0eab2b13d6f4fe3</actual>
        </checksum>
        <checksum>
          <type>sha256</type>
          <original>NO_ORIG</original>
          <actual>6e4556759dee675bdc21cd970886bf449c87159a7ae05082380b4df777007551</actual>
        </checksum>
      </checksums>
    </checksumsInfo>
  </additionalInfo>
</artifactory-file>