<?xml version='1.0' encoding='UTF-8'?>
<artifactory-file>
  <repoPath>
    <repoKey>nuget-remote-cache</repoKey>
    <path>System.Globalization.4.0.11.nupkg</path>
    <folder>false</folder>
  </repoPath>
  <name>System.Globalization.4.0.11.nupkg</name>
  <created>1578432215793</created>
  <lastModified>1544741985000</lastModified>
  <size>589139</size>
  <additionalInfo>
    <createdBy>uaxfwa</createdBy>
    <modifiedBy>uaxfwa</modifiedBy>
    <lastUpdated>1578432215794</lastUpdated>
    <checksumsInfo>
      <checksums>
        <checksum>
          <type>sha1</type>
          <actual>29d71dbab004882d15cecb0987017981773e8d7d</actual>
        </checksum>
        <checksum>
          <type>md5</type>
          <actual>5fbb61d117c57041555037457d9ebaa6</actual>
        </checksum>
        <checksum>
          <type>sha256</type>
          <original>NO_ORIG</original>
          <actual>adb4a07363c811cd9cdab37a2cadea0911005f70ea03636ad5670bad962c0c1c</actual>
        </checksum>
      </checksums>
    </checksumsInfo>
  </additionalInfo>
</artifactory-file>