<?xml version='1.0' encoding='UTF-8'?>
<artifactory-file>
  <repoPath>
    <repoKey>npm-remote-cache</repoKey>
    <path>last-run/-/last-run-1.1.1.tgz</path>
    <folder>false</folder>
  </repoPath>
  <name>last-run-1.1.1.tgz</name>
  <created>1576003399552</created>
  <lastModified>1527402528000</lastModified>
  <size>2870</size>
  <additionalInfo>
    <createdBy>dgqzdw</createdBy>
    <modifiedBy>dgqzdw</modifiedBy>
    <lastUpdated>1576003399552</lastUpdated>
    <checksumsInfo>
      <checksums>
        <checksum>
          <type>sha1</type>
          <actual>45b96942c17b1c79c772198259ba943bebf8ca5b</actual>
        </checksum>
        <checksum>
          <type>md5</type>
          <actual>323cb9363c87cc7a2a7bcde94b5b6efd</actual>
        </checksum>
        <checksum>
          <type>sha256</type>
          <original>NO_ORIG</original>
          <actual>635045ea1be06387e1507a16980badf5ce438462918cf63b31660233ff973b6a</actual>
        </checksum>
      </checksums>
    </checksumsInfo>
  </additionalInfo>
</artifactory-file>