<?xml version='1.0' encoding='UTF-8'?>
<artifactory-folder>
  <repoPath>
    <repoKey>npm-remote-cache</repoKey>
    <path>.npm/mochawesome-report-generator</path>
    <folder>true</folder>
  </repoPath>
  <name>mochawesome-report-generator</name>
  <created>1579828072809</created>
  <lastModified>1579828072809</lastModified>
  <additionalInfo>
    <createdBy>cvarjao@idir</createdBy>
    <modifiedBy>cvarjao@idir</modifiedBy>
    <lastUpdated>1579828072809</lastUpdated>
  </additionalInfo>
</artifactory-folder>