<?xml version='1.0' encoding='UTF-8'?>
<artifactory-file>
  <repoPath>
    <repoKey>pypi-remote-cache</repoKey>
    <path>.pypi/backoff.html</path>
    <folder>false</folder>
  </repoPath>
  <name>backoff.html</name>
  <created>1574023032671</created>
  <lastModified>1582154303800</lastModified>
  <size>10346</size>
  <additionalInfo>
    <createdBy>uhdbvk</createdBy>
    <modifiedBy>uhdbvk</modifiedBy>
    <lastUpdated>1582154303861</lastUpdated>
    <checksumsInfo>
      <checksums>
        <checksum>
          <type>sha1</type>
          <actual>abcfea4df3a2354220f9bed2a53835c162819c33</actual>
        </checksum>
        <checksum>
          <type>md5</type>
          <actual>be1a9f15d495fcaf35b6a120ed606bfc</actual>
        </checksum>
        <checksum>
          <type>sha256</type>
          <original>NO_ORIG</original>
          <actual>f88e6cabea3147b3e6c1ca245ed31c0e06731188b3bc1ea23de1b813b5ac84d4</actual>
        </checksum>
      </checksums>
    </checksumsInfo>
  </additionalInfo>
</artifactory-file>