<?xml version='1.0' encoding='UTF-8'?>
<properties>
  <artifactory.internal.etag>0x8D7403111710319</artifactory.internal.etag>
  <nuget.authors>Microsoft</nuget.authors>
  <nuget.copyright>© Microsoft Corporation. All rights reserved.</nuget.copyright>
  <nuget.dependency>Microsoft.Extensions.Caching.Abstractions:3.0.0:.NETCoreApp3.0</nuget.dependency>
  <nuget.dependency>Microsoft.Extensions.Caching.Abstractions:3.0.0:.NETStandard2.0</nuget.dependency>
  <nuget.dependency>Microsoft.Extensions.DependencyInjection.Abstractions:3.0.0:.NETCoreApp3.0</nuget.dependency>
  <nuget.dependency>Microsoft.Extensions.DependencyInjection.Abstractions:3.0.0:.NETStandard2.0</nuget.dependency>
  <nuget.dependency>Microsoft.Extensions.Logging.Abstractions:3.0.0:.NETCoreApp3.0</nuget.dependency>
  <nuget.dependency>Microsoft.Extensions.Logging.Abstractions:3.0.0:.NETStandard2.0</nuget.dependency>
  <nuget.dependency>Microsoft.Extensions.Options:3.0.0:.NETCoreApp3.0</nuget.dependency>
  <nuget.dependency>Microsoft.Extensions.Options:3.0.0:.NETStandard2.0</nuget.dependency>
  <nuget.description>In-memory cache implementation of Microsoft.Extensions.Caching.Memory.IMemoryCache.</nuget.description>
  <nuget.digest>JJdCoBiFgcwoUhK8YkeIqFRhsQQxKv+xcHOp/GqAIpZ9BLP5RuknGqq40mlcwbgZ3358MfkkEaTUfiYhjIQ56w==</nuget.digest>
  <nuget.iconUrl>https://go.microsoft.com/fwlink/?LinkID=288859</nuget.iconUrl>
  <nuget.id>Microsoft.Extensions.Caching.Memory</nuget.id>
  <nuget.licenseUrl>https://licenses.nuget.org/Apache-2.0</nuget.licenseUrl>
  <nuget.owners>Microsoft</nuget.owners>
  <nuget.projectUrl>https://asp.net/</nuget.projectUrl>
  <nuget.requireLicenseAcceptance>true</nuget.requireLicenseAcceptance>
  <nuget.tags>cache memorycache</nuget.tags>
  <nuget.version>3.0.0</nuget.version>
</properties>