<?xml version='1.0' encoding='UTF-8'?>
<artifactory-file>
  <repoPath>
    <repoKey>npm-remote-cache</repoKey>
    <path>.npm/matchdep/package.json</path>
    <folder>false</folder>
  </repoPath>
  <name>package.json</name>
  <created>1576003122320</created>
  <lastModified>1527406318000</lastModified>
  <size>12960</size>
  <additionalInfo>
    <createdBy>dgqzdw</createdBy>
    <modifiedBy>dgqzdw</modifiedBy>
    <lastUpdated>1586464386156</lastUpdated>
    <checksumsInfo>
      <checksums>
        <checksum>
          <type>sha1</type>
          <actual>a8991a3f08247f4728aa96d5f32133a27c78f741</actual>
        </checksum>
        <checksum>
          <type>md5</type>
          <actual>0ac1271d5a45a5a2729c4a30e170bd2a</actual>
        </checksum>
        <checksum>
          <type>sha256</type>
          <original>NO_ORIG</original>
          <actual>91738c52c860bf608dcb706f578507676cec4107fe0854b06822df0eed6b8f95</actual>
        </checksum>
      </checksums>
    </checksumsInfo>
  </additionalInfo>
</artifactory-file>