<?xml version='1.0' encoding='UTF-8'?>
<artifactory-file>
  <repoPath>
    <repoKey>npm-remote-cache</repoKey>
    <path>stream-transform/-/stream-transform-2.0.1.tgz</path>
    <folder>false</folder>
  </repoPath>
  <name>stream-transform-2.0.1.tgz</name>
  <created>1583960434019</created>
  <lastModified>1559992077000</lastModified>
  <size>6426</size>
  <additionalInfo>
    <createdBy>dgqzdw</createdBy>
    <modifiedBy>dgqzdw</modifiedBy>
    <lastUpdated>1583960434021</lastUpdated>
    <checksumsInfo>
      <checksums>
        <checksum>
          <type>sha1</type>
          <actual>112ef2b4d8b9b517f9a6994b0bf7b946fa4d51bc</actual>
        </checksum>
        <checksum>
          <type>md5</type>
          <actual>4371cf685a3e0bcb1f9a5499c03a4cb9</actual>
        </checksum>
        <checksum>
          <type>sha256</type>
          <original>NO_ORIG</original>
          <actual>b33a15e32dbd3a1496e26eaee9fd23c277e6c58cc83ef39941f43afb95dff15c</actual>
        </checksum>
      </checksums>
    </checksumsInfo>
  </additionalInfo>
</artifactory-file>