{
  "name" : "@types/istanbul-lib-report",
  "description" : "TypeScript definitions for istanbul-lib-report",
  "version" : "1.1.1",
  "repository" : {
    "type" : "git",
    "url" : "https://github.com/DefinitelyTyped/DefinitelyTyped.git",
    "directory" : "types/istanbul-lib-report"
  },
  "contributors" : [ {
    "name" : "Jason Cheatham",
    "url" : "https://github.com/jason0x43",
    "githubUsername" : "jason0x43"
  } ],
  "main" : "",
  "dist" : {
    "tarball" : "https://artifacts.developer.gov.bc.ca/artifactory/api/npm//npm-remote-cache/@types/istanbul-lib-report/-/istanbul-lib-report-1.1.1.tgz",
    "shasum" : "e5471e7fa33c61358dd38426189c037a58433b8c"
  },
  "dependencies" : {
    "@types/istanbul-lib-coverage" : "*"
  },
  "license" : "MIT",
  "scripts" : {
  },
  "types" : "index",
  "typeScriptVersion" : "2.4",
  "typesPublisherContentHash" : "64af305d196bdbb3cc44bc664daf0546df5c55bce234d53c29f97d0883da2f32"
}