<?xml version='1.0' encoding='UTF-8'?>
<artifactory-file>
  <repoPath>
    <repoKey>pypi-remote-cache</repoKey>
    <path>.pypi/attrs.html</path>
    <folder>false</folder>
  </repoPath>
  <name>attrs.html</name>
  <created>1574023031973</created>
  <lastModified>1582154270476</lastModified>
  <size>9260</size>
  <additionalInfo>
    <createdBy>uhdbvk</createdBy>
    <modifiedBy>uhdbvk</modifiedBy>
    <lastUpdated>1582154270532</lastUpdated>
    <checksumsInfo>
      <checksums>
        <checksum>
          <type>sha1</type>
          <actual>1aede6dfd05399a74b8d56f91f0a484d5e973796</actual>
        </checksum>
        <checksum>
          <type>md5</type>
          <actual>36f91f33519c1d436102824ff6f874e2</actual>
        </checksum>
        <checksum>
          <type>sha256</type>
          <original>NO_ORIG</original>
          <actual>e1c6a3e2dd06147d015efe9165e30cc1b4cd766cb91686a5a3db00dac22b954d</actual>
        </checksum>
      </checksums>
    </checksumsInfo>
  </additionalInfo>
</artifactory-file>