<?xml version='1.0' encoding='UTF-8'?>
<artifactory-file>
  <repoPath>
    <repoKey>npm-remote-cache</repoKey>
    <path>.npm/send/package.json</path>
    <folder>false</folder>
  </repoPath>
  <name>package.json</name>
  <created>1576003447082</created>
  <lastModified>1557538859000</lastModified>
  <size>106253</size>
  <additionalInfo>
    <createdBy>dgqzdw</createdBy>
    <modifiedBy>dgqzdw</modifiedBy>
    <lastUpdated>1586464331152</lastUpdated>
    <checksumsInfo>
      <checksums>
        <checksum>
          <type>sha1</type>
          <actual>8d89b89fc22654ed4083932e77c9ed16d8629178</actual>
        </checksum>
        <checksum>
          <type>md5</type>
          <actual>bf3c29ebbaf0309755baa3d2e69de77f</actual>
        </checksum>
        <checksum>
          <type>sha256</type>
          <original>NO_ORIG</original>
          <actual>8f9d35479b9fff19b8f87982f1de9e0e9fa1d3813ceec3a15450951874b4b26b</actual>
        </checksum>
      </checksums>
    </checksumsInfo>
  </additionalInfo>
</artifactory-file>