<?xml version='1.0' encoding='UTF-8'?>
<artifactory-file>
  <repoPath>
    <repoKey>npm-remote-cache</repoKey>
    <path>.npm/array-includes/package.json</path>
    <folder>false</folder>
  </repoPath>
  <name>package.json</name>
  <created>1576003432988</created>
  <lastModified>1585434349000</lastModified>
  <size>42249</size>
  <additionalInfo>
    <createdBy>dgqzdw</createdBy>
    <modifiedBy>dgqzdw</modifiedBy>
    <lastUpdated>1586464330828</lastUpdated>
    <checksumsInfo>
      <checksums>
        <checksum>
          <type>sha1</type>
          <actual>813e6365681170e141c2aae44a03f8a7d0acf4e7</actual>
        </checksum>
        <checksum>
          <type>md5</type>
          <actual>039c4e0c29fc28a71911453128896cbf</actual>
        </checksum>
        <checksum>
          <type>sha256</type>
          <original>NO_ORIG</original>
          <actual>c703a258eb414714783b9c6d14387f4047a2b6cb13e820eb9f3b1bf313545629</actual>
        </checksum>
      </checksums>
    </checksumsInfo>
  </additionalInfo>
</artifactory-file>