<?xml version='1.0' encoding='UTF-8'?>
<artifactory-file>
  <repoPath>
    <repoKey>npm-remote-cache</repoKey>
    <path>is-descriptor/-/is-descriptor-1.0.2.tgz</path>
    <folder>false</folder>
  </repoPath>
  <name>is-descriptor-1.0.2.tgz</name>
  <created>1576003621819</created>
  <lastModified>1527397130000</lastModified>
  <size>2995</size>
  <additionalInfo>
    <createdBy>dgqzdw</createdBy>
    <modifiedBy>dgqzdw</modifiedBy>
    <lastUpdated>1576003621873</lastUpdated>
    <checksumsInfo>
      <checksums>
        <checksum>
          <type>sha1</type>
          <actual>3b159746a66604b04f8c81524ba365c5f14d86ec</actual>
        </checksum>
        <checksum>
          <type>md5</type>
          <actual>7cd33adcb4ca927942b08b261badd3ed</actual>
        </checksum>
        <checksum>
          <type>sha256</type>
          <original>NO_ORIG</original>
          <actual>fe5ee7a359c2ae4ec7c12a075d903150c23365bf55c0c471b8d34fade96c6ead</actual>
        </checksum>
      </checksums>
    </checksumsInfo>
  </additionalInfo>
</artifactory-file>