<?xml version='1.0' encoding='UTF-8'?>
<artifactory-folder>
  <repoPath>
    <repoKey>pypi-remote-cache</repoKey>
    <path>b3/ac/304005fbc13c49dac4767e9733a1f25701e08b1ee0b66fd8f6e07339c921</path>
    <folder>true</folder>
  </repoPath>
  <name>304005fbc13c49dac4767e9733a1f25701e08b1ee0b66fd8f6e07339c921</name>
  <created>1574023481291</created>
  <lastModified>1574023481291</lastModified>
  <additionalInfo>
    <createdBy>uhdbvk</createdBy>
    <modifiedBy>uhdbvk</modifiedBy>
    <lastUpdated>1574023481291</lastUpdated>
  </additionalInfo>
</artifactory-folder>