{
  "name" : "through2",
  "description" : "A tiny wrapper around Node.js streams.Transform (Streams2/3) to avoid explicit subclassing noise",
  "version" : "3.0.1",
  "author" : "Rod Vagg <r@va.gg> (https://github.com/rvagg)",
  "repository" : {
    "type" : "git",
    "url" : "https://github.com/rvagg/through2.git"
  },
  "main" : "through2.js",
  "dist" : {
    "tarball" : "https://artifacts.developer.gov.bc.ca/artifactory/api/npm//npm-remote-cache/through2/-/through2-3.0.1.tgz",
    "shasum" : "39276e713c3302edf9e388dd9c812dd3b825bd5a"
  },
  "dependencies" : {
    "readable-stream" : "2 || 3"
  },
  "devDependencies" : {
    "bl" : "~2.0.1",
    "faucet" : "0.0.1",
    "nyc" : "~13.1.0",
    "stream-spigot" : "~3.0.6",
    "tape" : "~4.9.1"
  },
  "keywords" : [ "stream", "streams2", "through", "transform" ],
  "license" : "MIT",
  "scripts" : {
    "test" : "nyc node test/test.js | faucet && nyc report"
  }
}