<?xml version='1.0' encoding='UTF-8'?>
<artifactory-file>
  <repoPath>
    <repoKey>npm-remote-cache</repoKey>
    <path>resolve-dir/-/resolve-dir-1.0.1.tgz</path>
    <folder>false</folder>
  </repoPath>
  <name>resolve-dir-1.0.1.tgz</name>
  <created>1576003128313</created>
  <lastModified>1527436495000</lastModified>
  <size>2560</size>
  <additionalInfo>
    <createdBy>dgqzdw</createdBy>
    <modifiedBy>dgqzdw</modifiedBy>
    <lastUpdated>1576003128314</lastUpdated>
    <checksumsInfo>
      <checksums>
        <checksum>
          <type>sha1</type>
          <actual>79a40644c362be82f26effe739c9bb5382046f43</actual>
        </checksum>
        <checksum>
          <type>md5</type>
          <actual>b89ce9749afea75459c09cf0ebec4f35</actual>
        </checksum>
        <checksum>
          <type>sha256</type>
          <original>NO_ORIG</original>
          <actual>f2a8c238c975b4527d24dd757954e655c04c81152c5cb5a13af0f5937ebbeaaf</actual>
        </checksum>
      </checksums>
    </checksumsInfo>
  </additionalInfo>
</artifactory-file>