<?xml version='1.0' encoding='UTF-8'?>
<artifactory-file>
  <repoPath>
    <repoKey>npm-remote-cache</repoKey>
    <path>.npm/term-size/package.json</path>
    <folder>false</folder>
  </repoPath>
  <name>package.json</name>
  <created>1576003129180</created>
  <lastModified>1580399795000</lastModified>
  <size>18722</size>
  <additionalInfo>
    <createdBy>dgqzdw</createdBy>
    <modifiedBy>dgqzdw</modifiedBy>
    <lastUpdated>1586464322666</lastUpdated>
    <checksumsInfo>
      <checksums>
        <checksum>
          <type>sha1</type>
          <actual>741a3fd1094f90002793404b77c5a3eb6be9556c</actual>
        </checksum>
        <checksum>
          <type>md5</type>
          <actual>967408f4bc6c0a4596d4f4e3e2586670</actual>
        </checksum>
        <checksum>
          <type>sha256</type>
          <original>NO_ORIG</original>
          <actual>bd95dcbc2903fd5e88767e47821779f142cb15a47e310bda9d5360afb0d19cf1</actual>
        </checksum>
      </checksums>
    </checksumsInfo>
  </additionalInfo>
</artifactory-file>