<?xml version='1.0' encoding='UTF-8'?>
<artifactory-file>
  <repoPath>
    <repoKey>pypi-remote-cache</repoKey>
    <path>81/98/801900ea24536928a99e40a815812c1bc7d7f833d53ec53f216d8330db7d/freezegun-0.3.12-py2.py3-none-any.whl</path>
    <folder>false</folder>
  </repoPath>
  <name>freezegun-0.3.12-py2.py3-none-any.whl</name>
  <created>1574023472289</created>
  <lastModified>1559181736000</lastModified>
  <size>12179</size>
  <additionalInfo>
    <createdBy>uhdbvk</createdBy>
    <modifiedBy>uhdbvk</modifiedBy>
    <lastUpdated>1574023472290</lastUpdated>
    <checksumsInfo>
      <checksums>
        <checksum>
          <type>sha1</type>
          <actual>46c1ed05b0d929619bebcee5680aab67e5f94445</actual>
        </checksum>
        <checksum>
          <type>md5</type>
          <actual>6a9809078dd3993bedffad152c76e74d</actual>
        </checksum>
        <checksum>
          <type>sha256</type>
          <original>NO_ORIG</original>
          <actual>edfdf5bc6040969e6ed2e36eafe277963bdc8b7c01daeda96c5c8594576c9390</actual>
        </checksum>
      </checksums>
    </checksumsInfo>
  </additionalInfo>
</artifactory-file>