{
  "name" : "parse-json",
  "description" : "Parse JSON with more helpful errors",
  "version" : "2.2.0",
  "author" : {
    "name" : "Sindre Sorhus",
    "email" : "sindresorhus@gmail.com",
    "url" : "sindresorhus.com"
  },
  "repository" : "sindresorhus/parse-json",
  "engines" : {
    "node" : ">=0.10.0"
  },
  "dist" : {
    "tarball" : "https://artifacts.developer.gov.bc.ca/artifactory/api/npm//npm-remote-cache/parse-json/-/parse-json-2.2.0.tgz",
    "shasum" : "f480f40434ef80741f8469099f8dea18f55a4dc9"
  },
  "dependencies" : {
    "error-ex" : "^1.2.0"
  },
  "devDependencies" : {
    "ava" : "0.0.4",
    "xo" : "*"
  },
  "keywords" : [ "parse", "json", "graceful", "error", "message", "humanize", "friendly", "helpful", "string", "str" ],
  "license" : "MIT",
  "files" : [ "index.js", "vendor" ],
  "scripts" : {
    "test" : "xo && node test.js"
  },
  "xo" : {
    "ignores" : [ "vendor/**" ]
  }
}