{
  "name" : "parse5",
  "description" : "HTML parser and serializer.",
  "version" : "5.1.0",
  "author" : "Ivan Nikulin <ifaaan@gmail.com> (https://github.com/inikulin)",
  "homepage" : "https://github.com/inikulin/parse5",
  "repository" : {
    "type" : "git",
    "url" : "git://github.com/inikulin/parse5.git"
  },
  "contributors" : "https://github.com/inikulin/parse5/graphs/contributors",
  "main" : "./lib/index.js",
  "dist" : {
    "tarball" : "https://artifacts.developer.gov.bc.ca/artifactory/api/npm//npm-remote-cache/parse5/-/parse5-5.1.0.tgz",
    "shasum" : "c59341c9723f414c452975564c7c00a68d58acd2"
  },
  "keywords" : [ "html", "parser", "html5", "WHATWG", "specification", "fast", "html parser", "html5 parser", "htmlparser", "parse5", "serializer", "html serializer", "htmlserializer", "parse", "serialize" ],
  "license" : "MIT",
  "files" : [ "lib" ],
  "scripts" : {
  }
}