<?xml version='1.0' encoding='UTF-8'?>
<artifactory-file>
  <repoPath>
    <repoKey>npm-remote-cache</repoKey>
    <path>.npm/object-assign/package.json</path>
    <folder>false</folder>
  </repoPath>
  <name>package.json</name>
  <created>1576003403577</created>
  <lastModified>1527418646000</lastModified>
  <size>24020</size>
  <additionalInfo>
    <createdBy>dgqzdw</createdBy>
    <modifiedBy>dgqzdw</modifiedBy>
    <lastUpdated>1586464331212</lastUpdated>
    <checksumsInfo>
      <checksums>
        <checksum>
          <type>sha1</type>
          <actual>a551578b36af2abdb5e7a9664478a76a4cdbdf6c</actual>
        </checksum>
        <checksum>
          <type>md5</type>
          <actual>d7609bf70dc4cde24cf456be05d80a7c</actual>
        </checksum>
        <checksum>
          <type>sha256</type>
          <original>NO_ORIG</original>
          <actual>0b995347e8b8e1a9d3670d240d46729ff95450b3ae957506c2ff68127002d5e4</actual>
        </checksum>
      </checksums>
    </checksumsInfo>
  </additionalInfo>
</artifactory-file>